aliceblueantpy/__init__.py
aliceblueantpy/aliceblueapi.py
aliceblueantpy-2.0.0.dist-info/LICENSE.txt
aliceblueantpy-2.0.0.dist-info/METADATA
aliceblueantpy-2.0.0.dist-info/WHEEL
aliceblueantpy-2.0.0.dist-info/top_level.txt
aliceblueantpy-2.0.0.dist-info/RECORD
