Metadata-Version: 2.1
Name: aliceblueantpy
Version: 2.0.0
Summary: Python SDK for API users
Home-page: https://a3.aliceblueonline.com/
Author: Codifi
Author-email: pradeep@codifi.in
License: MIT
Platform: UNKNOWN
Classifier: Programming Language :: Python :: 3.9
Classifier: License :: OSI Approved :: MIT License
Classifier: Operating System :: OS Independent
Classifier: Natural Language :: English
Classifier: Intended Audience :: Developers
Requires-Python: >=3.9
License-File: LICENSE.txt
Requires-Dist: numpy
